resanter_logger/__init__.py
resanter_logger/re_logger.py
resanter_logger-0.0.5.dist-info/LICENSE
resanter_logger-0.0.5.dist-info/METADATA
resanter_logger-0.0.5.dist-info/WHEEL
resanter_logger-0.0.5.dist-info/top_level.txt
resanter_logger-0.0.5.dist-info/RECORD
